cora_ui/__about__.py
cora_ui/__init__.py
cora_ui/__main__.py
cora_ui-0.0.1.dist-info/METADATA
cora_ui-0.0.1.dist-info/WHEEL
cora_ui-0.0.1.dist-info/entry_points.txt
cora_ui-0.0.1.dist-info/top_level.txt
cora_ui-0.0.1.dist-info/RECORD
