Metadata-Version: 2.1
Name: cora-ui
Version: 0.0.1
Summary: Touchscreen interface for Cora virtual assistant
Home-page: https://heycora.com
Author: Stephen Vondenstein
Author-email: stephen@vondenstein.com
License: UNKNOWN
Keywords: cora virtual assistant siri google alexa snips mycroft
Platform: UNKNOWN
Classifier: Topic :: Home Automation
Classifier: Development Status :: 2 - Pre-Alpha
Classifier: License :: Other/Proprietary License
Classifier: Programming Language :: Python :: 3 :: Only
Classifier: Operating System :: POSIX :: Linux
Classifier: Operating System :: Unix
Classifier: Environment :: X11 Applications
Classifier: Intended Audience :: End Users/Desktop
Classifier: Natural Language :: English
Requires-Python: >=3.5.*, <4
Requires-Dist: termcolor
